polspectra.py
Polspectra-1.1.0.dist-info/LICENSE
Polspectra-1.1.0.dist-info/METADATA
Polspectra-1.1.0.dist-info/WHEEL
Polspectra-1.1.0.dist-info/top_level.txt
Polspectra-1.1.0.dist-info/RECORD
