Metadata-Version: 2.1
Name: Polspectra
Version: 1.1.0
Summary: Reading, writing, and manipulating radio astronomy polarization (Stokes) spectra.
Home-page: https://github.com/CIRADA-Tools/PolSpectra
Maintainer: Cameron Van Eck
Maintainer-email: cameron.van.eck@utoronto.ca
License: MIT
Platform: UNKNOWN
Classifier: Development Status :: 5 - Production/Stable
Classifier: License :: OSI Approved :: MIT License
Classifier: Programming Language :: Python
Classifier: Programming Language :: Python :: 3
Classifier: Programming Language :: Python :: 3.6
Classifier: Intended Audience :: Science/Research
Classifier: Topic :: Scientific/Engineering :: Astronomy
Requires-Python: >=3.5.0
License-File: LICENSE
Requires-Dist: numpy
Requires-Dist: astropy
